hdruk_schema/__init__.py
hdruk_schema/accessibility.py
hdruk_schema/coverage.py
hdruk_schema/documentation.py
hdruk_schema/enrinchmentAndLinkage.py
hdruk_schema/identifier.py
hdruk_schema/issued.py
hdruk_schema/modified.py
hdruk_schema/observations.py
hdruk_schema/provenance.py
hdruk_schema/revisions.py
hdruk_schema/schema_validator.py
hdruk_schema/structuralMetadata.py
hdruk_schema/summary.py
hdruk_schema/version.py
hdruk_schema-0.1.14.dist-info/WHEEL
hdruk_schema-0.1.14.dist-info/METADATA
hdruk_schema-0.1.14.dist-info/RECORD
