Metadata-Version: 2.1
Name: hdruk-schema
Version: 0.1.14
Summary: 
Author: Ibrahim Animashaun
Author-email: iaanimashaun@gmail.com
Requires-Python: >=3.7,<4.0
Classifier: Programming Language :: Python :: 3
Classifier: Programming Language :: Python :: 3.10
Classifier: Programming Language :: Python :: 3.7
Classifier: Programming Language :: Python :: 3.8
Classifier: Programming Language :: Python :: 3.9
Requires-Dist: pandas (>=1.0.0,<2.0.0)
Requires-Dist: prettytable (>=3.3.0,<4.0.0)
Requires-Dist: termcolor (>=1.1.0,<2.0.0)
Requires-Dist: validate_email (>=1.3,<2.0)
Requires-Dist: validators (>=0.20.0,<0.21.0)
